[
  {
    "id": "cca_sweep",
    "name": "CCA Counterair Sweep",
    "description": "CCAs and F-22/F-35s conduct airspace denial through distributed formations and electronic deception.",
    "mapImage": "images/map_sweep.jpg",
    "phases": [
      {
        "name": "Launch",
        "positions": [
          {
            "id": "f22",
            "x": 200,
            "y": 400
          },
          {
            "id": "f35",
            "x": 220,
            "y": 420
          },
          {
            "id": "cca2",
            "x": 240,
            "y": 440
          },
          {
            "id": "cca5",
            "x": 260,
            "y": 460
          },
          {
            "id": "cca11",
            "x": 280,
            "y": 480
          }
        ]
      },
      {
        "name": "En Route",
        "positions": [
          {
            "id": "f22",
            "x": 320,
            "y": 280
          },
          {
            "id": "f35",
            "x": 360,
            "y": 320
          },
          {
            "id": "cca2",
            "x": 380,
            "y": 340
          },
          {
            "id": "cca5",
            "x": 400,
            "y": 360
          },
          {
            "id": "cca11",
            "x": 420,
            "y": 380
          }
        ]
      },
      {
        "name": "Engagement",
        "positions": [
          {
            "id": "f22",
            "x": 480,
            "y": 180
          },
          {
            "id": "f35",
            "x": 500,
            "y": 200
          },
          {
            "id": "cca2",
            "x": 520,
            "y": 160
          },
          {
            "id": "cca5",
            "x": 560,
            "y": 300
          },
          {
            "id": "cca11",
            "x": 600,
            "y": 220
          }
        ]
      },
      {
        "name": "Egress",
        "positions": [
          {
            "id": "f22",
            "x": 360,
            "y": 260
          },
          {
            "id": "f35",
            "x": 380,
            "y": 280
          },
          {
            "id": "cca2",
            "x": 400,
            "y": 300
          },
          {
            "id": "cca5",
            "x": 420,
            "y": 320
          },
          {
            "id": "cca11",
            "x": 440,
            "y": 340
          }
        ]
      }
    ],
    "links": [
      {
        "source": "f22",
        "target": "cca2"
      },
      {
        "source": "cca2",
        "target": "cca5"
      },
      {
        "source": "f35",
        "target": "cca11"
      }
    ]
  },
  {
    "id": "hvaa_protect",
    "name": "HVAA Protection & Ambush Alert",
    "description": "CCAs, F-15s, and E-7 provide overwatch and intercept hostile AEW&C threats.",
    "mapImage": "images/map_hvaa.jpg",
    "phases": [
      {
        "name": "Launch",
        "positions": [
          {
            "id": "f15",
            "x": 180,
            "y": 360
          },
          {
            "id": "e7a",
            "x": 160,
            "y": 380
          },
          {
            "id": "cca1",
            "x": 200,
            "y": 400
          },
          {
            "id": "cca6",
            "x": 220,
            "y": 420
          },
          {
            "id": "cca11",
            "x": 240,
            "y": 440
          }
        ]
      },
      {
        "name": "Patrol",
        "positions": [
          {
            "id": "f15",
            "x": 320,
            "y": 280
          },
          {
            "id": "e7a",
            "x": 300,
            "y": 340
          },
          {
            "id": "cca1",
            "x": 360,
            "y": 260
          },
          {
            "id": "cca6",
            "x": 380,
            "y": 180
          },
          {
            "id": "cca11",
            "x": 340,
            "y": 360
          }
        ]
      },
      {
        "name": "Ambush",
        "positions": [
          {
            "id": "f15",
            "x": 460,
            "y": 280
          },
          {
            "id": "e7a",
            "x": 380,
            "y": 340
          },
          {
            "id": "cca1",
            "x": 540,
            "y": 260
          },
          {
            "id": "cca6",
            "x": 620,
            "y": 180
          },
          {
            "id": "cca11",
            "x": 500,
            "y": 360
          }
        ]
      },
      {
        "name": "RTB",
        "positions": [
          {
            "id": "f15",
            "x": 300,
            "y": 300
          },
          {
            "id": "e7a",
            "x": 240,
            "y": 360
          },
          {
            "id": "cca1",
            "x": 280,
            "y": 380
          },
          {
            "id": "cca6",
            "x": 260,
            "y": 320
          },
          {
            "id": "cca11",
            "x": 220,
            "y": 340
          }
        ]
      }
    ],
    "links": [
      {
        "source": "f15",
        "target": "cca1"
      },
      {
        "source": "cca6",
        "target": "e7a"
      },
      {
        "source": "cca11",
        "target": "f15"
      }
    ]
  },
  {
    "id": "sead_wave",
    "name": "SEAD Pressure Waves",
    "description": "Multi-phase SEAD operations using loitering munitions, EW CCAs, and ISR platforms to degrade coastal IADS.",
    "mapImage": "images/map_sead.jpg",
    "phases": [
      {
        "name": "Staging",
        "positions": [
          {
            "id": "rc135",
            "x": 160,
            "y": 360
          },
          {
            "id": "cca4",
            "x": 180,
            "y": 160
          },
          {
            "id": "cca7",
            "x": 200,
            "y": 240
          },
          {
            "id": "cca9",
            "x": 220,
            "y": 320
          },
          {
            "id": "cca12",
            "x": 240,
            "y": 400
          }
        ]
      },
      {
        "name": "Push Forward",
        "positions": [
          {
            "id": "rc135",
            "x": 300,
            "y": 280
          },
          {
            "id": "cca4",
            "x": 380,
            "y": 160
          },
          {
            "id": "cca7",
            "x": 420,
            "y": 240
          },
          {
            "id": "cca9",
            "x": 460,
            "y": 320
          },
          {
            "id": "cca12",
            "x": 480,
            "y": 400
          }
        ]
      },
      {
        "name": "Strike",
        "positions": [
          {
            "id": "rc135",
            "x": 400,
            "y": 280
          },
          {
            "id": "cca4",
            "x": 480,
            "y": 160
          },
          {
            "id": "cca7",
            "x": 580,
            "y": 240
          },
          {
            "id": "cca9",
            "x": 620,
            "y": 320
          },
          {
            "id": "cca12",
            "x": 520,
            "y": 400
          }
        ]
      },
      {
        "name": "Assess & Exit",
        "positions": [
          {
            "id": "rc135",
            "x": 300,
            "y": 260
          },
          {
            "id": "cca4",
            "x": 360,
            "y": 180
          },
          {
            "id": "cca7",
            "x": 380,
            "y": 240
          },
          {
            "id": "cca9",
            "x": 400,
            "y": 320
          },
          {
            "id": "cca12",
            "x": 420,
            "y": 380
          }
        ]
      }
    ],
    "links": [
      {
        "source": "cca4",
        "target": "rc135"
      },
      {
        "source": "cca7",
        "target": "cca12"
      },
      {
        "source": "cca9",
        "target": "rc135"
      }
    ]
  }
]